{
  "project_info": {
    "project_number": "906995647281",
    "project_id": "wechat-f677a",
    "storage_bucket": "wechat-f677a.appspot.com"
  },
  "client": [
    {
      "client_info": {
        "mobilesdk_app_id": "1:906995647281:android:a20a6d21b9a7661b386610",
        "android_client_info": {
          "package_name": "com.example.wechat"
        }
      },
      "oauth_client": [
        {
          "client_id": "906995647281-ial53h82muhgi60131utqh9osbfsqhg9.apps.googleusercontent.com",
          "client_type": 1,
          "android_info": {
            "package_name": "com.example.wechat",
            "certificate_hash": "9621ffa038346ab6e662cb3d95d3a3594cf59ab2"
          }
        },
        {
          "client_id": "906995647281-4dfmfir6pr8j6tearjij4fvmci4srqoc.apps.googleusercontent.com",
          "client_type": 3
        }
      ],
      "api_key": [
        {
          "current_key": "AIzaSyAHX8A6P_qVXY3ymLvyn7XtAlvFZMh1-pk"
        }
      ],
      "services": {
        "appinvite_service": {
          "other_platform_oauth_client": [
            {
              "client_id": "906995647281-4dfmfir6pr8j6tearjij4fvmci4srqoc.apps.googleusercontent.com",
              "client_type": 3
            },
            {
              "client_id": "906995647281-14vqlvt65278bfteesbg3a69o7q8uep1.apps.googleusercontent.com",
              "client_type": 2,
              "ios_info": {
                "bundle_id": "com.example.wechat"
              }
            }
          ]
        }
      }
    }
  ],
  "configuration_version": "1"
}